fastcms/__init__.py
fastcms/models/__init__.py
fastcms/models/mixins.py
fastcms/schemas/__init__.py
fastcms/schemas/db.py
fastcms/services/__init__.py
fastcms/services/db.py
fastcms/storages/__init__.py
fastcms/storages/base.py
fastcms/storages/exceptions.py
fastcms/storages/local.py
fastcms/storages/s3.py
fastcms/utils/__init__.py
fastcms/utils/crypto.py
fastcms/utils/db.py
fastcms/utils/jwt.py
fastcms/utils/logging.py
fastcms/utils/text.py
fastcms/utils/time.py
fastcms/utils/version.py
fastcms-0.1.0.dist-info/licenses/LICENSE
fastcms-0.1.0.dist-info/WHEEL
fastcms-0.1.0.dist-info/METADATA
fastcms-0.1.0.dist-info/RECORD
