Metadata-Version: 2.4
Name: fastcms
Version: 0.1.0
Summary: FastCMS - A FastAPI-based Content Management System and FastAPI reusables for faster and better development.
Author-email: "Azat (@azataiot)" <8280770+azataiot@users.noreply.github.com>
Requires-Python: >=3.13
License-Expression: MIT
License-File: LICENSE
Requires-Dist: aioboto3>=14.3.0
Requires-Dist: aiofiles>=24.1.0
Requires-Dist: fastapi>=0.115.12
Requires-Dist: passlib[argon2, bcrypt]>=1.7.4
Requires-Dist: pydantic>=2.11.5
Requires-Dist: pyjwt>=2.10.1
Requires-Dist: python-ulid[pydantic]>=3.0.0
Requires-Dist: sqlmodel>=0.0.24
Project-URL: Home, https://azgh.cc/fastcms/
